source_translator/__init__.py
source_translator/c_like.py
source_translator/language_slug.py
source_translator/naming.py
source_translator/python_source.py
source_translator/langs/cpp.py
source_translator/langs/php.py
source_translator/langs/ts.py
source_translator-1.1.0.data/scripts/source_translate.py
source_translator-1.1.0.dist-info/licenses/COPYING
source_translator-1.1.0.dist-info/METADATA
source_translator-1.1.0.dist-info/WHEEL
source_translator-1.1.0.dist-info/top_level.txt
source_translator-1.1.0.dist-info/RECORD
