Metadata-Version: 2.4
Name: source_translator
Version: 1.1.0
Summary: Module to translate Python source code into other programming languages
Home-page: https://gitlab.com/mattbas/python-source-translator
Author: Mattia "Glax" Basaglia
Author-email: dev@dragon.best
Project-URL: Bug Reports, https://gitlab.com/mattbas/python-source-translator/-/issues
Project-URL: Source, https://gitlab.com/mattbas/python-source-translator
Keywords: transpiling,source convertion
Classifier: Development Status :: 5 - Production/Stable
Classifier: Intended Audience :: Developers
Classifier: License :: OSI Approved :: GNU General Public License v3 or later (GPLv3+)
Classifier: Programming Language :: Python :: 3
Classifier: Programming Language :: Python :: 3 :: Only
Classifier: Operating System :: OS Independent
Classifier: Topic :: Software Development
Classifier: Programming Language :: C++
Classifier: Programming Language :: JavaScript
Classifier: Programming Language :: PHP
Requires-Python: >=3.9, <4
License-File: COPYING
Dynamic: author
Dynamic: author-email
Dynamic: classifier
Dynamic: description
Dynamic: description-content-type
Dynamic: home-page
Dynamic: keywords
Dynamic: license-file
Dynamic: project-url
Dynamic: requires-python
Dynamic: summary
